[  {
  "title": "Komi Cant Communicate",
  "author": "Tomohito Oda",
  "publisher": "Shogakukan Shonen Sunday Comics",
  "year": 2016,
  "pages": 32
 },
 {
  "title": "Demon Slayer",
  "author": "Koyoharu Gotoge",
  "publisher": "Shueisha",
  "year": 2016,
  "pages": 48
 },
 {
  "title": "Shadows House",
  "author": "Somato",
  "publisher": "Shueisha",
  "year": 2018,
  "pages": 32
 },
{
  "title": "The Quintessential Quintuplets",
  "author": "Negi Haruba",
  "publisher": "Kodansha Shonen Magazine Comics",
  "year": 2019,
  "pages": 48
 }
]